sora/__init__.py
sora/sora.py
sora_python-0.1.2.dist-info/METADATA
sora_python-0.1.2.dist-info/WHEEL
sora_python-0.1.2.dist-info/top_level.txt
sora_python-0.1.2.dist-info/RECORD
