Metadata-Version: 2.1
Name: sora-python
Version: 0.1.2
Summary: Python client for Sora ID: soraid.com
Home-page: UNKNOWN
Author: Sora ID, Inc.
Author-email: support@soraid.com
License: UNKNOWN
Platform: UNKNOWN
Classifier: Programming Language :: Python :: 3
Classifier: Operating System :: OS Independent
Requires-Python: >=3.7
Requires-Dist: requests (>=2.24)
